<?xml version="1.0" encoding="UTF-8"?>
<!-- Edited with XRT Chief Observer Tool version 0.9x12 (1304) -->
<!DOCTYPE PROG SYSTEM "XRTPRG.dtd">
<PROG>
  <modified author="ISHIBASHI, Bish" dateTime="2007-05-11T08:53:30Z" />
  <name>Synoptic - multi-filter FW1 / FW2 - part B</name>
  <COT_info deleted="FALSE" lastUsed="2007-05-11T08:53:30Z" version="1388" locked="FALSE"
    tag="09D57DA9082C/1388" COTversion="0.9x12" COTbuild="1304" Mutable="TRUE" />
  <COT_slot>-1</COT_slot>
  <COT_reserved>0</COT_reserved>
  <MAIN_RPT>1</MAIN_RPT>
  <MAIN>
    <MAIN_ENTRY POS="1">
      <Call>1</Call>
      <COT_SUBR>Subr-1</COT_SUBR>
      <Repeat>1</Repeat>
      <Interval>1</Interval>
    </MAIN_ENTRY>
  </MAIN>
  <SUBR NO="1">
  <COT_SUBR>Subr-1</COT_SUBR>
    <SUBR_ENTRY POS="1">
      <Call>0</Call>
      <COT_SEQ>BEC721C930AC/2496</COT_SEQ>
      <Repeat>1</Repeat>
      <Interval>4</Interval>
    </SUBR_ENTRY>
  </SUBR>
  <SUBR NO="2">
  </SUBR>
  <SUBR NO="3">
  </SUBR>
  <SUBR NO="4">
  </SUBR>
</PROG>
