<?xml version="1.0" encoding="UTF-8"?>
<!-- Edited with XRT Chief Observer Tool version 0.9x14 (1312) -->
<!DOCTYPE SEQN SYSTEM "XRTSEQ.dtd">
<SEQN>
  <modified author="MASUDA, Satoshi" dateTime="2007-09-04T07:10:33Z" />
  <name>Synoptic Al/poly short (362ms)/long (4096ms) pair-2</name>
  <COT_info deleted="FALSE" lastUsed="2007-09-04T07:10:33Z" version="253F" locked="FALSE"
    tag="5A4665CBD72A/253F" COTversion="0.9x14" COTbuild="1312" Mutable="TRUE" />
  <COT_slot>-1</COT_slot>
  <COT_AEC>NOT USED</COT_AEC>
  <COT_ROI>NOT USED</COT_ROI>
  <COT_CMP>NOT USED</COT_CMP>
  <SEQN_ENTRY POS="1">
    <PARM_NO>25</PARM_NO>
    <COT_PARM>00000C6F1F37/35DE</COT_PARM>
    <REGN_NO>11</REGN_NO>
    <COT_fov preflare="false" hcenter="1024" vcenter="1024" width="2048" height="2048" />
    <COMP_CODE>0x728</COMP_CODE>
    <AEC_NO>0</AEC_NO>
    <BUF_NO>0</BUF_NO>
    <DMF>0</DMF>
    <SEQN_INT>4</SEQN_INT>
  </SEQN_ENTRY>
  <SEQN_ENTRY POS="2">
    <PARM_NO>45</PARM_NO>
    <COT_PARM>00007E1195B5/35D3</COT_PARM>
    <REGN_NO>11</REGN_NO>
    <COT_fov preflare="false" hcenter="1024" vcenter="1024" width="2048" height="2048" />
    <COMP_CODE>0x728</COMP_CODE>
    <AEC_NO>0</AEC_NO>
    <BUF_NO>0</BUF_NO>
    <DMF>0</DMF>
    <SEQN_INT>4</SEQN_INT>
  </SEQN_ENTRY>
</SEQN>
