<?xml version="1.0" encoding="UTF-8"?>
<!-- Edited with XRT Chief Observer Tool version 2.0x40 (2080) -->
<!DOCTYPE PROG SYSTEM "XRTPRG.dtd">
<PROG>
  <modified author="MASUDA, Satoshi" dateTime="2016-03-07T06:27:16Z" />
  <name>Eclipse2016309_only_thin_Be_movie-duration-15min-10s cad</name>
  <COT_info deleted="FALSE" lastUsed="2016-03-07T08:15:08Z" version="1B1A" locked="FALSE"
    tag="15B468C0F322/1B1A" COTversion="2.0x40" COTbuild="2080" Mutable="TRUE" />
  <COT_slot>-1</COT_slot>
  <COT_reserved>0</COT_reserved>
  <MAIN_RPT>1</MAIN_RPT>
  <MAIN>
    <MAIN_ENTRY POS="1">
      <Call>2</Call>
      <COT_SUBR>Subr-B</COT_SUBR>
      <Repeat>1</Repeat>
      <Interval>4</Interval>
    </MAIN_ENTRY>
  </MAIN>
  <SUBR NO="1">
  <COT_SUBR>Subr-A</COT_SUBR>
    <SUBR_ENTRY POS="1">
      <Call>27</Call>
      <COT_SEQ>E08264C90DEA/2DC4</COT_SEQ>
      <Repeat>1</Repeat>
      <Interval>4</Interval>
    </SUBR_ENTRY>
  </SUBR>
  <SUBR NO="2">
  <COT_SUBR>Subr-B</COT_SUBR>
    <SUBR_ENTRY POS="1">
      <Call>22</Call>
      <COT_SEQ>879A4EC4A921/2DC3</COT_SEQ>
      <Repeat>90</Repeat>
      <Interval>20</Interval>
    </SUBR_ENTRY>
  </SUBR>
  <SUBR NO="3">
  <COT_SUBR>Subr-C</COT_SUBR>
    <SUBR_ENTRY POS="1">
      <Call>1</Call>
      <COT_SEQ>655A6270E3BD/2D13</COT_SEQ>
      <Repeat>1</Repeat>
      <Interval>4</Interval>
    </SUBR_ENTRY>
  </SUBR>
  <SUBR NO="4">
  <COT_SUBR>Subr-D</COT_SUBR>
  </SUBR>
</PROG>
