<?xml version="1.0" encoding="UTF-8"?>
<!-- Edited with XRT Chief Observer Tool version 2.0x40 (2080) -->
<!DOCTYPE PARM SYSTEM "XRTPAR.dtd">
<PARM>
  <modified author="KOTOKU, Junichi" dateTime="2008-12-15T03:07:44Z" />
  <name>Al/poly - 1x1 - 11571ms-2</name>
  <COT_info deleted="FALSE" lastUsed="2008-12-15T03:07:09Z" version="37B0" locked="FALSE"
    tag="9F5E6C9E9A3A/37B0" COTversion="2.0x40" COTbuild="2080" Mutable="TRUE" />
  <COT_slot>-1</COT_slot>
  <FltA_L1>1</FltA_L1>
  <FltB_L1>0</FltB_L1>
  <FltA_L2>1</FltA_L2>
  <FltB_L2>0</FltB_L2>
  <AspectShutter>0</AspectShutter>
  <ShutterMode>0</ShutterMode>
  <ImageType>0</ImageType>
  <Exposure>26</Exposure>
  <Calibration>0</Calibration>
  <Resolution>0</Resolution>
</PARM>
