<?xml version="1.0" encoding="UTF-8"?>
<!-- Edited with XRT Chief Observer Tool version 2.0x40 (2080) -->
<!DOCTYPE SEQN SYSTEM "XRTSEQ.dtd">
<SEQN>
  <modified author="TESTA, Paola" dateTime="2011-03-04T19:59:31Z" />
  <name>Flare thin-Be/med-Al/thick-Be 384x384 - Al-poly/Ti-poly 1024x1024 (2x2)</name>
  <COT_info deleted="FALSE" lastUsed="2011-03-12T02:34:09Z" version="2B22" locked="FALSE"
    tag="E0562B8AFAC7/2B22" COTversion="2.0x40" COTbuild="2080" Mutable="TRUE" />
  <COT_slot>-1</COT_slot>
  <COT_AEC>NOT USED</COT_AEC>
  <COT_ROI>NOT USED</COT_ROI>
  <COT_CMP>NOT USED</COT_CMP>
  <SEQN_ENTRY POS="1">
    <PARM_NO>56</PARM_NO>
    <COT_PARM>000074C1DE18/353C</COT_PARM>
    <REGN_NO>15</REGN_NO>
    <COT_fov FOV_type="flare1" hcenter="1024" vcenter="1024" width="384" height="384" />
    <COMP_CODE>0x72c</COMP_CODE>
    <AEC_NO>3</AEC_NO>
    <BUF_NO>0</BUF_NO>
    <DMF>0</DMF>
    <SEQN_INT>4</SEQN_INT>
  </SEQN_ENTRY>
  <SEQN_ENTRY POS="2">
    <PARM_NO>36</PARM_NO>
    <COT_PARM>8E6712EE6168/3875</COT_PARM>
    <REGN_NO>15</REGN_NO>
    <COT_fov FOV_type="flare1" hcenter="1024" vcenter="1024" width="384" height="384" />
    <COMP_CODE>0x72c</COMP_CODE>
    <AEC_NO>3</AEC_NO>
    <BUF_NO>0</BUF_NO>
    <DMF>0</DMF>
    <SEQN_INT>4</SEQN_INT>
  </SEQN_ENTRY>
  <SEQN_ENTRY POS="3">
    <PARM_NO>30</PARM_NO>
    <COT_PARM>FCDC76EB9897/3836</COT_PARM>
    <REGN_NO>15</REGN_NO>
    <COT_fov FOV_type="flare1" hcenter="1024" vcenter="1024" width="384" height="384" />
    <COMP_CODE>0x72c</COMP_CODE>
    <AEC_NO>3</AEC_NO>
    <BUF_NO>0</BUF_NO>
    <DMF>0</DMF>
    <SEQN_INT>4</SEQN_INT>
  </SEQN_ENTRY>
  <SEQN_ENTRY POS="4">
    <PARM_NO>10</PARM_NO>
    <COT_PARM>65AD3D73D528/3721</COT_PARM>
    <REGN_NO>16</REGN_NO>
    <COT_fov FOV_type="flare2" hcenter="1024" vcenter="1024" width="512" height="512" />
    <COMP_CODE>0x72c</COMP_CODE>
    <AEC_NO>2</AEC_NO>
    <BUF_NO>0</BUF_NO>
    <DMF>0</DMF>
    <SEQN_INT>4</SEQN_INT>
  </SEQN_ENTRY>
  <SEQN_ENTRY POS="5">
    <PARM_NO>13</PARM_NO>
    <COT_PARM>C5212C5C3F9F/3742</COT_PARM>
    <REGN_NO>16</REGN_NO>
    <COT_fov FOV_type="flare2" hcenter="1024" vcenter="1024" width="512" height="512" />
    <COMP_CODE>0x72c</COMP_CODE>
    <AEC_NO>2</AEC_NO>
    <BUF_NO>0</BUF_NO>
    <DMF>0</DMF>
    <SEQN_INT>4</SEQN_INT>
  </SEQN_ENTRY>
</SEQN>
