<?xml version="1.0" encoding="UTF-8"?>
<!-- Edited with XRT Chief Observer Tool version 2.0x40 (2080) -->
<!DOCTYPE SEQN SYSTEM "XRTSEQ.dtd">
<SEQN>
  <modified author="ISHIBASHI, Bish" dateTime="2022-04-15T05:58:00Z" />
  <name>WICKED Al/Poly (Thin-Be), Thin-Be (Med-Be), long/short pairs - 768x192FOV - 784 1048 for AR</name>
  <COT_info deleted="FALSE" lastUsed="2022-04-18T03:36:33Z" version="2ECB" locked="FALSE"
    tag="16C1325488DD/2ECB" COTversion="2.0x40" COTbuild="2080" Mutable="TRUE" />
  <COT_slot>-1</COT_slot>
  <COT_AEC>NOT USED</COT_AEC>
  <COT_ROI>NOT USED</COT_ROI>
  <COT_CMP>NOT USED</COT_CMP>
  <SEQN_ENTRY POS="1">
    <PARM_NO>56</PARM_NO>
    <COT_PARM>E28D0DDB43E8/38D5</COT_PARM>
    <REGN_NO>11</REGN_NO>
    <COT_fov FOV_type="normal" hcenter="784" vcenter="1048" width="768" height="192" />
    <COMP_CODE>0x72c</COMP_CODE>
    <AEC_NO>2</AEC_NO>
    <BUF_NO>0</BUF_NO>
    <DMF>0</DMF>
    <SEQN_INT>4</SEQN_INT>
  </SEQN_ENTRY>
  <SEQN_ENTRY POS="2">
    <PARM_NO>56</PARM_NO>
    <COT_PARM>E28D0DDB43E8/38D5</COT_PARM>
    <REGN_NO>11</REGN_NO>
    <COT_fov FOV_type="normal" hcenter="784" vcenter="1048" width="768" height="192" />
    <COMP_CODE>0x72c</COMP_CODE>
    <AEC_NO>3</AEC_NO>
    <BUF_NO>0</BUF_NO>
    <DMF>0</DMF>
    <SEQN_INT>4</SEQN_INT>
  </SEQN_ENTRY>
  <SEQN_ENTRY POS="3">
    <PARM_NO>68</PARM_NO>
    <COT_PARM>000031D95721/3527</COT_PARM>
    <REGN_NO>11</REGN_NO>
    <COT_fov FOV_type="normal" hcenter="784" vcenter="1048" width="768" height="192" />
    <COMP_CODE>0x72c</COMP_CODE>
    <AEC_NO>2</AEC_NO>
    <BUF_NO>0</BUF_NO>
    <DMF>0</DMF>
    <SEQN_INT>4</SEQN_INT>
  </SEQN_ENTRY>
  <SEQN_ENTRY POS="4">
    <PARM_NO>68</PARM_NO>
    <COT_PARM>000031D95721/3527</COT_PARM>
    <REGN_NO>11</REGN_NO>
    <COT_fov FOV_type="normal" hcenter="784" vcenter="1048" width="768" height="192" />
    <COMP_CODE>0x72c</COMP_CODE>
    <AEC_NO>3</AEC_NO>
    <BUF_NO>0</BUF_NO>
    <DMF>0</DMF>
    <SEQN_INT>4</SEQN_INT>
  </SEQN_ENTRY>
</SEQN>
